LICENSE
README.md
setup.py
DtoLib/__init__.py
DtoLib/abstract_dto.py
DtoLib/dto_field.py
DtoLib/exceptions.py
DtoLib.egg-info/PKG-INFO
DtoLib.egg-info/SOURCES.txt
DtoLib.egg-info/dependency_links.txt
DtoLib.egg-info/top_level.txt